cell_typist/__init__.py
cell_typist/core/__init__.py
cell_typist/core/datatypes.py
cell_typist/core/experiment.py
cell_typist/core/merge.py
cell_typist/core/serializer.py
cell_typist/measure/__init__.py
cell_typist/measure/measure.py
cell_typist/preprocess/__init__.py
cell_typist/preprocess/feature_extraction.py
cell_typist/tests/__init__.py
cell_typist/tests/test_load_experiments.py
cell_typist/tests/core/__init__.py
cell_typist/tests/core/test_datatypes.py
cell_typist/tests/core/test_experiment.py
cell_typist/tests/core/test_serializer.py
cell_typist/tests/measure/__init__.py
cell_typist/tests/measure/test_measure.py
cell_typist/tests/preprocess/__init__.py
cell_typist/tests/preprocess/test_feature_extraction.py
cell_typist/tests/view/__init__.py
cell_typist/tests/view/test_factories.py
cell_typist/tests/view/test_plot.py
cell_typist/view/__init__.py
cell_typist/view/factories.py
cell_typist/view/plot.py
hcr_cell_typist-0.1.1.dist-info/LICENSE
hcr_cell_typist-0.1.1.dist-info/METADATA
hcr_cell_typist-0.1.1.dist-info/WHEEL
hcr_cell_typist-0.1.1.dist-info/top_level.txt
hcr_cell_typist-0.1.1.dist-info/RECORD
