Metadata-Version: 2.1
Name: hcr-cell-typist
Version: 0.1.1
Summary: A library to aid cell type classification in HCR experiments, downstream of QuPath
Author-email: Luca Masin <luca.masin@kuleuven.be>
License: Copyright 2024 Luca Masin
Classifier: Programming Language :: Python :: 3
Classifier: License :: OSI Approved :: MIT License
Classifier: Operating System :: OS Independent
License-File: LICENSE
Requires-Dist: pandas >=2.1.4
Requires-Dist: numpy >=1.26.3
Requires-Dist: matplotlib >=3.8.2
Requires-Dist: seaborn >=0.13.1
Requires-Dist: scikit-image >=0.22.0
Requires-Dist: openpyxl >=3.0.10
Requires-Dist: pytest >=7.4.0
Requires-Dist: pytest-cov >=4.1.0
Requires-Dist: jupyter >=1.0.0
